lemniscat/plugin/filetransform/__init__.py
lemniscat/plugin/filetransform/filetransform.py
lemniscat/plugin/filetransform/main.py
lemniscat/plugin/filetransform/plugin.yaml
lemniscat/plugin/filetransform/requirements.txt
lemniscat_plugin_filetransform-0.3.0.dist-info/licenses/LICENSE
lemniscat_plugin_filetransform-0.3.0.dist-info/METADATA
lemniscat_plugin_filetransform-0.3.0.dist-info/WHEEL
lemniscat_plugin_filetransform-0.3.0.dist-info/top_level.txt
lemniscat_plugin_filetransform-0.3.0.dist-info/RECORD
