Metadata-Version: 2.4
Name: lemniscat.plugin.filetransform
Version: 0.3.0
Summary: A plugin for lemniscat to transform files
Author-email: Philippe MORISSEAU <philippe.morisseau@outlook.com>
License: MIT
Project-URL: Homepage, https://github.com/lemniscat-devops/lemniscat.plugin.filetransform
Project-URL: Issues, https://github.com/lemniscat-devops/lemniscat.plugin.filetransform/issues
Classifier: Programming Language :: Python :: 3
Classifier: License :: OSI Approved :: MIT License
Classifier: Operating System :: OS Independent
Requires-Python: >=3.10
License-File: LICENSE
Requires-Dist: lemniscat.core>=0.2.1
Requires-Dist: PyYAML==6.0.1
Requires-Dist: pytz==2023.3
Requires-Dist: python-hcl2>=4.3.0
Dynamic: license-file
